src/__init__.py
src/gene2tab.py
gene2tab-0.1.5.dist-info/LICENSE
gene2tab-0.1.5.dist-info/METADATA
gene2tab-0.1.5.dist-info/WHEEL
gene2tab-0.1.5.dist-info/entry_points.txt
gene2tab-0.1.5.dist-info/top_level.txt
gene2tab-0.1.5.dist-info/RECORD
