Metadata-Version: 2.1
Name: gene2tab
Version: 0.1.5
Summary: Creates a table with the presence/absence of genes in samples
Home-page: https://github.com/ikergarcia1996/Gene2Tab
Author: Iker García-Ferrero
Author-email: igarciaf896@gmail.com
License: Apache License 2.0
License-File: LICENSE
Requires-Dist: tabulate
Requires-Dist: pandas
